worklog/__init__.py
worklog/cli.py
worklog/hledger_completer.py
worklog/timeclock.py
worklog_cli-1.0.0.dist-info/METADATA
worklog_cli-1.0.0.dist-info/WHEEL
worklog_cli-1.0.0.dist-info/entry_points.txt
worklog_cli-1.0.0.dist-info/RECORD
