Metadata-Version: 2.3
Name: worklog-cli
Version: 1.0.0
Summary: A personal time-tracking system
License: MIT
Author: Chris Proctor
Author-email: chris@chrisproctor.net
Requires-Python: >=3.10,<4.0
Classifier: License :: OSI Approved :: MIT License
Classifier: Programming Language :: Python :: 3
Classifier: Programming Language :: Python :: 3.10
Classifier: Programming Language :: Python :: 3.11
Classifier: Programming Language :: Python :: 3.12
Classifier: Programming Language :: Python :: 3.13
Requires-Dist: arrow (>=1.3.0,<2.0.0)
Project-URL: Repository, https://github.com/cproctor/worklog
